FSI_DQ/AnomalyDetectionNB.py
FSI_DQ/Anomaly_multivariateNB.py
FSI_DQ/StandardizationNB.py
FSI_DQ/__init__.py
FSI_DQ/__main__.py
FSI_DQ/business_contextNB.py
FSI_DQ-1.0.1.dist-info/LICENSE
FSI_DQ-1.0.1.dist-info/METADATA
FSI_DQ-1.0.1.dist-info/WHEEL
FSI_DQ-1.0.1.dist-info/top_level.txt
FSI_DQ-1.0.1.dist-info/RECORD
