Metadata-Version: 2.1
Name: FSI_DQ
Version: 1.0.1
Summary: DQ Solution to answer all DQ needs.
Home-page: https://github.com/pypa/FSI_DQ
Author: Utkarsh Banyal
Author-email: utkarsh.banyal@neudesic.com
Project-URL: Bug Tracker, https://github.com/pypa/FSI_DQ/issues
Classifier: Programming Language :: Python :: 3
Classifier: License :: OSI Approved :: MIT License
Classifier: Operating System :: OS Independent
Requires-Python: >=3.6
License-File: LICENSE
Requires-Dist: findspark
Requires-Dist: langchain
Requires-Dist: openai
Requires-Dist: scikit-learn
Requires-Dist: tabulate
Requires-Dist: langchain-experimental
Requires-Dist: azure.storage.blob
